autoteachable/README.md
autoteachable/autoteachable.py
autoteachable/config.py
autoteachable/config.py_bk
autoteachable/health_check.py
autoteachable/requirements.txt
autoteachable-0.3.dist-info/METADATA
autoteachable-0.3.dist-info/WHEEL
autoteachable-0.3.dist-info/entry_points.txt
autoteachable-0.3.dist-info/top_level.txt
autoteachable-0.3.dist-info/RECORD
